README.md
setup.py
src/ctpros/__init__.py
src/ctpros/__main__.py
src/ctpros.egg-info/PKG-INFO
src/ctpros.egg-info/SOURCES.txt
src/ctpros.egg-info/dependency_links.txt
src/ctpros.egg-info/requires.txt
src/ctpros.egg-info/top_level.txt
src/ctpros/graphics/__init__.py
src/ctpros/graphics/main.py
src/ctpros/graphics/components/__init__.py
src/ctpros/graphics/components/backend.py
src/ctpros/graphics/components/imgframe.py
src/ctpros/graphics/components/infoframe.py
src/ctpros/graphics/components/menu.py
src/ctpros/graphics/components/progressbar.py
src/ctpros/graphics/components/tools.py
src/ctpros/img/__init__.py
src/ctpros/img/classes.py
src/ctpros/img/methods.py
src/ctpros/img/utils/__init__.py
src/ctpros/img/utils/components.py
src/ctpros/img/utils/decorators.py
src/ctpros/img/utils/script.py
src/ctpros/protocols/__init__.py
src/ctpros/protocols/stitch.py