Metadata-Version: 2.1
Name: ctpros
Version: 0.1.3
Summary: Computed Tomography Processing Registration Open Sourced
Home-page: https://gitlab.com/caosuna/ctpros
Author: Carlos Osuna
Author-email: charlie@caosuna.com
License: UNKNOWN
Platform: UNKNOWN
Requires-Python: >=3.7.0, <=3.8.0
